[
    {
        "id": "ST15-01",
        "name": "Koromon",
        "cardImage": "assets/images/cards/jap/ST15-01.webp",
        "cardType": "Digi-Egg",
        "dp": "-",
        "playCost": "-",
        "digivolveCost1": "-",
        "digivolveColor1": "-",
        "digivolveLevel1": "-",
        "digivolveCost2": "-",
        "digivolveColor2": "-",
        "digivolveLevel2": "-",
        "cardLv": "Lv.2",
        "form": "In-Training",
        "attribute": "-",
        "type": "Lesser",
        "rarity": "U",
        "cardNumber": "ST15-01",
        "digiXros": "-",
        "specialDigivolve": "-",
        "dnaDigivolve": "-",
        "effect": "-",
        "digivolveEffect": "[All Turns] [Once Per Turn] When an attack target is switched, this Digimon gets +1000 DP for the turn.",
        "securityEffect": "-",
        "aceEffect": "-",
        "notes": "▹START DECK WAR DRAGON OF COURAGE [ST-15]",
        "color": "Black",
        "version": "Normal",
        "illustrator": "sasasi",
        "block": [
            "03"
        ],
        "restriction": "-"
    },
    {
        "id": "ST15-02",
        "name": "Agumon",
        "cardImage": "assets/images/cards/jap/ST15-02.webp",
        "cardType": "Digimon",
        "dp": "1000",
        "playCost": "3",
        "digivolveCost1": "0 from Lv.2",
        "digivolveColor1": "Black",
        "digivolveLevel1": "2",
        "digivolveCost2": "-",
        "digivolveColor2": "-",
        "digivolveLevel2": "-",
        "cardLv": "Lv.3",
        "form": "Rookie",
        "attribute": "Vaccine",
        "type": "Reptile",
        "rarity": "R",
        "cardNumber": "ST15-02",
        "digiXros": "-",
        "specialDigivolve": "[Digivolve] From [Koromon]: Cost 0",
        "dnaDigivolve": "-",
        "effect": "[Start of Your Main Phase] If your opponent has a Digimon, gain 1 memory.",
        "digivolveEffect": "[All Turns] [Once Per Turn] When an attack target is switched, gain 1 memory.",
        "securityEffect": "-",
        "aceEffect": "-",
        "notes": "▹START DECK WAR DRAGON OF COURAGE [ST-15]",
        "color": "Black",
        "version": "Normal",
        "illustrator": "sasasi",
        "block": [
            "03"
        ],
        "restriction": "-"
    },
    {
        "id": "ST15-03",
        "name": "ClearAgumon",
        "cardImage": "assets/images/cards/jap/ST15-03.webp",
        "cardType": "Digimon",
        "dp": "2000",
        "playCost": "3",
        "digivolveCost1": "0 from Lv.2",
        "digivolveColor1": "Black",
        "digivolveLevel1": "2",
        "digivolveCost2": "-",
        "digivolveColor2": "-",
        "digivolveLevel2": "-",
        "cardLv": "Lv.3",
        "form": "Rookie",
        "attribute": "Vaccine",
        "type": "Puppet",
        "rarity": "U",
        "cardNumber": "ST15-03",
        "digiXros": "-",
        "specialDigivolve": "-",
        "dnaDigivolve": "-",
        "effect": "-",
        "digivolveEffect": "＜Reboot＞ (Unsuspend this Digimon during your opponent's unsuspend phase).",
        "securityEffect": "-",
        "aceEffect": "-",
        "notes": "▹START DECK WAR DRAGON OF COURAGE [ST-15]",
        "color": "Black",
        "version": "Normal",
        "illustrator": "",
        "block": [
            "03"
        ],
        "restriction": "-"
    },
    {
        "id": "ST15-04",
        "name": "Solarmon",
        "cardImage": "assets/images/cards/jap/ST15-04.webp",
        "cardType": "Digimon",
        "dp": "2000",
        "playCost": "3",
        "digivolveCost1": "0 from Lv.2",
        "digivolveColor1": "Black",
        "digivolveLevel1": "2",
        "digivolveCost2": "-",
        "digivolveColor2": "-",
        "digivolveLevel2": "-",
        "cardLv": "Lv.3",
        "form": "Rookie",
        "attribute": "Vaccine",
        "type": "Machine",
        "rarity": "C",
        "cardNumber": "ST15-04",
        "digiXros": "-",
        "specialDigivolve": "-",
        "dnaDigivolve": "-",
        "effect": "[On Play] Reveal the top card of your deck. If it is a black card, add it to your hand. Trash the rest.",
        "digivolveEffect": "-",
        "securityEffect": "-",
        "aceEffect": "-",
        "notes": "▹START DECK WAR DRAGON OF COURAGE [ST-15]",
        "color": "Black",
        "version": "Normal",
        "illustrator": "",
        "block": [
            "03"
        ],
        "restriction": "-"
    },
    {
        "id": "ST15-05",
        "name": "ToyAgumon",
        "cardImage": "assets/images/cards/jap/ST15-05.webp",
        "cardType": "Digimon",
        "dp": "4000",
        "playCost": "4",
        "digivolveCost1": "0 from Lv.2",
        "digivolveColor1": "Black",
        "digivolveLevel1": "2",
        "digivolveCost2": "-",
        "digivolveColor2": "-",
        "digivolveLevel2": "-",
        "cardLv": "Lv.3",
        "form": "Rookie",
        "attribute": "Vaccine",
        "type": "Puppet",
        "rarity": "C",
        "cardNumber": "ST15-05",
        "digiXros": "-",
        "specialDigivolve": "-",
        "dnaDigivolve": "-",
        "effect": "＜Blocker＞ (When an opponent's Digimon attacks, you may suspend this Digimon to force the opponent to attack it instead).\n[Your Turn] When this Digimon attacks a player, lose 2 memory.",
        "digivolveEffect": "-",
        "securityEffect": "-",
        "aceEffect": "-",
        "notes": "▹START DECK WAR DRAGON OF COURAGE [ST-15]",
        "color": "Black",
        "version": "Normal",
        "illustrator": "GOSSAN",
        "block": [
            "03"
        ],
        "restriction": "-"
    },
    {
        "id": "ST15-06",
        "name": "Mekanorimon",
        "cardImage": "assets/images/cards/jap/ST15-06.webp",
        "cardType": "Digimon",
        "dp": "5000",
        "playCost": "4",
        "digivolveCost1": "2 from Lv.3",
        "digivolveColor1": "Black",
        "digivolveLevel1": "3",
        "digivolveCost2": "-",
        "digivolveColor2": "-",
        "digivolveLevel2": "-",
        "cardLv": "Lv.4",
        "form": "Champion",
        "attribute": "Virus",
        "type": "Machine",
        "rarity": "C",
        "cardNumber": "ST15-06",
        "digiXros": "-",
        "specialDigivolve": "-",
        "dnaDigivolve": "-",
        "effect": "-",
        "digivolveEffect": "＜Reboot＞ (Unsuspend this Digimon during your opponent's unsuspend phase).",
        "securityEffect": "-",
        "aceEffect": "-",
        "notes": "▹START DECK WAR DRAGON OF COURAGE [ST-15]",
        "color": "Black",
        "version": "Normal",
        "illustrator": "koki",
        "block": [
            "03"
        ],
        "restriction": "-"
    },
    {
        "id": "ST15-07",
        "name": "Tankmon",
        "cardImage": "assets/images/cards/jap/ST15-07.webp",
        "cardType": "Digimon",
        "dp": "6000",
        "playCost": "5",
        "digivolveCost1": "2 from Lv.3",
        "digivolveColor1": "Black",
        "digivolveLevel1": "3",
        "digivolveCost2": "-",
        "digivolveColor2": "-",
        "digivolveLevel2": "-",
        "cardLv": "Lv.4",
        "form": "Champion",
        "attribute": "Data",
        "type": "Cyborg",
        "rarity": "C",
        "cardNumber": "ST15-07",
        "digiXros": "-",
        "specialDigivolve": "-",
        "dnaDigivolve": "-",
        "effect": "＜Jamming＞ (This Digimon can't be deleted in battles against Security Digimon).",
        "digivolveEffect": "-",
        "securityEffect": "-",
        "aceEffect": "-",
        "notes": "▹START DECK WAR DRAGON OF COURAGE [ST-15]",
        "color": "Black",
        "version": "Normal",
        "illustrator": "poroze",
        "block": [
            "03"
        ],
        "restriction": "-"
    },
    {
        "id": "ST15-08",
        "name": "Greymon",
        "cardImage": "assets/images/cards/jap/ST15-08.webp",
        "cardType": "Digimon",
        "dp": "5000",
        "playCost": "6",
        "digivolveCost1": "2 from Lv.3",
        "digivolveColor1": "Black",
        "digivolveLevel1": "3",
        "digivolveCost2": "-",
        "digivolveColor2": "-",
        "digivolveLevel2": "-",
        "cardLv": "Lv.4",
        "form": "Champion",
        "attribute": "Vaccine",
        "type": "Dinosaur",
        "rarity": "SR",
        "cardNumber": "ST15-08",
        "digiXros": "-",
        "specialDigivolve": "[Digivolve] From Lv.3 w/[Agumon] in name: Cost 2",
        "dnaDigivolve": "-",
        "effect": "[Security] You may play 1 [Agumon] or Tamer card with [Tai Kamiya] in its name from your hand or trash without paying the cost.\n＜Blocker＞ (When an opponent's Digimon attacks, you may suspend this Digimon to force the opponent to attack it instead).",
        "digivolveEffect": "[All Turns] [Once Per Turn] When an attack target is switched, gain 1 memory.",
        "securityEffect": "-",
        "aceEffect": "-",
        "notes": "▹START DECK WAR DRAGON OF COURAGE [ST-15]",
        "color": "Black",
        "version": "Normal",
        "illustrator": "sasasi",
        "block": [
            "03"
        ],
        "restriction": "-"
    },
    {
        "id": "ST15-09",
        "name": "Knightmon",
        "cardImage": "assets/images/cards/jap/ST15-09.webp",
        "cardType": "Digimon",
        "dp": "7000",
        "playCost": "6",
        "digivolveCost1": "3 from Lv.4",
        "digivolveColor1": "Black",
        "digivolveLevel1": "4",
        "digivolveCost2": "-",
        "digivolveColor2": "-",
        "digivolveLevel2": "-",
        "cardLv": "Lv.5",
        "form": "Ultimate",
        "attribute": "Data",
        "type": "Warrior",
        "rarity": "C",
        "cardNumber": "ST15-09",
        "digiXros": "-",
        "specialDigivolve": "-",
        "dnaDigivolve": "-",
        "effect": "[On Play] Delete 1 of your opponent's Digimon with a play cost of 5 or less.",
        "digivolveEffect": "-",
        "securityEffect": "-",
        "aceEffect": "-",
        "notes": "▹START DECK WAR DRAGON OF COURAGE [ST-15]",
        "color": "Black",
        "version": "Normal",
        "illustrator": "Spareribs",
        "block": [
            "03"
        ],
        "restriction": "-"
    },
    {
        "id": "ST15-10",
        "name": "Andromon",
        "cardImage": "assets/images/cards/jap/ST15-10.webp",
        "cardType": "Digimon",
        "dp": "7000",
        "playCost": "7",
        "digivolveCost1": "3 from Lv.4",
        "digivolveColor1": "Black",
        "digivolveLevel1": "4",
        "digivolveCost2": "-",
        "digivolveColor2": "-",
        "digivolveLevel2": "-",
        "cardLv": "Lv.5",
        "form": "Ultimate",
        "attribute": "Vaccine",
        "type": "Cyborg",
        "rarity": "U",
        "cardNumber": "ST15-10",
        "digiXros": "-",
        "specialDigivolve": "-",
        "dnaDigivolve": "-",
        "effect": "[When Digivolving] ＜De-Digivolve  1＞ on 1 of your opponent's Digimon (Trash up to 1 card from the top of one of your opponent's Digimon. If it has no digivolution cards, or becomes a level 3 Digimon, you can't trash any more cards).",
        "digivolveEffect": "＜Reboot＞ (Unsuspend this Digimon during your opponent's unsuspend phase).",
        "securityEffect": "-",
        "aceEffect": "-",
        "notes": "▹START DECK WAR DRAGON OF COURAGE [ST-15]",
        "color": "Black",
        "version": "Normal",
        "illustrator": "GOSSAN",
        "block": [
            "03"
        ],
        "restriction": "-"
    },
    {
        "id": "ST15-11",
        "name": "MetalGreymon",
        "cardImage": "assets/images/cards/jap/ST15-11.webp",
        "cardType": "Digimon",
        "dp": "8000",
        "playCost": "8",
        "digivolveCost1": "3 from Lv.4",
        "digivolveColor1": "Black",
        "digivolveLevel1": "4",
        "digivolveCost2": "-",
        "digivolveColor2": "-",
        "digivolveLevel2": "-",
        "cardLv": "Lv.5",
        "form": "Ultimate",
        "attribute": "Vaccine",
        "type": "Cyborg",
        "rarity": "R",
        "cardNumber": "ST15-11",
        "digiXros": "-",
        "specialDigivolve": "[Digivolve] From Lv.4 w/[Greymon] in name: Cost 3",
        "dnaDigivolve": "-",
        "effect": "＜Blocker＞ (When an opponent's Digimon attacks, you may suspend this Digimon to force the opponent to attack it instead).",
        "digivolveEffect": "＜S Attack +1＞ (This Digimon checks 1 additional security card).",
        "securityEffect": "-",
        "aceEffect": "-",
        "notes": "▹START DECK WAR DRAGON OF COURAGE [ST-15]",
        "color": "Black",
        "version": "Normal",
        "illustrator": "sasasi",
        "block": [
            "03"
        ],
        "restriction": "-"
    },
    {
        "id": "ST15-12",
        "name": "WarGreymon ACE",
        "cardImage": "assets/images/cards/jap/ST15-12.webp",
        "cardType": "Digimon",
        "dp": "11000",
        "playCost": "6",
        "digivolveCost1": "3 from Lv.5",
        "digivolveColor1": "Black",
        "digivolveLevel1": "5",
        "digivolveCost2": "-",
        "digivolveColor2": "-",
        "digivolveLevel2": "-",
        "cardLv": "Lv.6",
        "form": "Mega",
        "attribute": "Vaccine",
        "type": "Dragonkin",
        "rarity": "SR",
        "cardNumber": "ST15-12",
        "digiXros": "-",
        "specialDigivolve": "[Digivolve] From Lv.5 w/[Greymon] in name: Cost 3",
        "dnaDigivolve": "-",
        "effect": "[Hand] [Counter] ＜Blast Digivolve＞ (Your Digimon may digivolve into this card without paying the cost).\n[All Turns] [Once Per Turn] When either players' security is reduced, you may unsuspend this Digimon.",
        "digivolveEffect": "-",
        "securityEffect": "-",
        "aceEffect": "Overflow ＜-4＞ (When this card is sent from battle area or under your card to another area, lose 4 memory).",
        "notes": "▹START DECK WAR DRAGON OF COURAGE [ST-15]",
        "color": "Black",
        "version": "Normal",
        "illustrator": "sasasi",
        "block": [
            "03"
        ],
        "restriction": "-"
    },
    {
        "id": "ST15-13",
        "name": "HiAndromon",
        "cardImage": "assets/images/cards/jap/ST15-13.webp",
        "cardType": "Digimon",
        "dp": "12000",
        "playCost": "11",
        "digivolveCost1": "4 from Lv.5",
        "digivolveColor1": "Black",
        "digivolveLevel1": "5",
        "digivolveCost2": "-",
        "digivolveColor2": "-",
        "digivolveLevel2": "-",
        "cardLv": "Lv.6",
        "form": "Mega",
        "attribute": "Vaccine",
        "type": "Cyborg",
        "rarity": "U",
        "cardNumber": "ST15-13",
        "digiXros": "-",
        "specialDigivolve": "-",
        "dnaDigivolve": "-",
        "effect": "＜Blocker＞ (When an opponent's Digimon attacks, you may suspend this Digimon to force the opponent to attack it instead).\n[When Digivolving] Delete 1 of your opponent's Digimon with a play cost of 8 or less.",
        "digivolveEffect": "-",
        "securityEffect": "-",
        "aceEffect": "-",
        "notes": "▹START DECK WAR DRAGON OF COURAGE [ST-15]",
        "color": "Black",
        "version": "Normal",
        "illustrator": "Kazumasa Yasukuni",
        "block": [
            "03"
        ],
        "restriction": "-"
    },
    {
        "id": "ST15-14",
        "name": "Tai Kamiya",
        "cardImage": "assets/images/cards/jap/ST15-14.webp",
        "cardType": "Tamer",
        "dp": "-",
        "playCost": "4",
        "digivolveCost1": "-",
        "digivolveColor1": "-",
        "digivolveLevel1": "-",
        "digivolveCost2": "-",
        "digivolveColor2": "-",
        "digivolveLevel2": "-",
        "cardLv": "-",
        "form": "-",
        "attribute": "-",
        "type": "-",
        "rarity": "R",
        "cardNumber": "ST15-14",
        "digiXros": "-",
        "specialDigivolve": "-",
        "dnaDigivolve": "-",
        "effect": "[Start of Your Turn] If you have 2 memory or less, set your memory to 3.\n[All Turns] When an attack target is switched, by suspending this Tamer, ＜Draw 1＞ (Draw 1 card from your deck) and 1 of your Digimon gets +2000 DP for the turn.",
        "digivolveEffect": "-",
        "securityEffect": "[Security] Play this card without paying its memory cost.",
        "aceEffect": "-",
        "notes": "▹START DECK WAR DRAGON OF COURAGE [ST-15]",
        "color": "Black",
        "version": "Normal",
        "illustrator": "",
        "block": [
            "03"
        ],
        "restriction": "-"
    },
    {
        "id": "ST15-15",
        "name": "Advance of Courage",
        "cardImage": "assets/images/cards/jap/ST15-15.webp",
        "cardType": "Option",
        "dp": "-",
        "playCost": "4",
        "digivolveCost1": "-",
        "digivolveColor1": "-",
        "digivolveLevel1": "-",
        "digivolveCost2": "-",
        "digivolveColor2": "-",
        "digivolveLevel2": "-",
        "cardLv": "-",
        "form": "-",
        "attribute": "-",
        "type": "-",
        "rarity": "U",
        "cardNumber": "ST15-15",
        "digiXros": "-",
        "specialDigivolve": "-",
        "dnaDigivolve": "-",
        "effect": "While you have a Tamer with [Tai Kamiya] in its name, you may use this card without meeting its color requirements.\n[Main] Unsuspend 1 of your Digimon. Then, 1 of your Digimon with [Greymon] in its name is not affected by your opponent's Digimon's effects until the end of your opponent's turn.",
        "digivolveEffect": "-",
        "securityEffect": "[Security] Activate this card's [Main] effect.",
        "aceEffect": "-",
        "notes": "▹START DECK WAR DRAGON OF COURAGE [ST-15]",
        "color": "Black",
        "version": "Normal",
        "illustrator": "",
        "block": [
            "03"
        ],
        "restriction": "-"
    },
    {
        "id": "ST15-16",
        "name": "Trident Arm",
        "cardImage": "assets/images/cards/jap/ST15-16.webp",
        "cardType": "Option",
        "dp": "-",
        "playCost": "6",
        "digivolveCost1": "-",
        "digivolveColor1": "-",
        "digivolveLevel1": "-",
        "digivolveCost2": "-",
        "digivolveColor2": "-",
        "digivolveLevel2": "-",
        "cardLv": "-",
        "form": "-",
        "attribute": "-",
        "type": "-",
        "rarity": "C",
        "cardNumber": "ST15-16",
        "digiXros": "-",
        "specialDigivolve": "-",
        "dnaDigivolve": "-",
        "effect": "[Main] ＜De-Digivolve  3＞ on 1 of your opponent's Digimon (Trash up to 3 cards from the top of one of your opponent's Digimon. If it has no digivolution cards, or becomes a level 3 Digimon, you can't trash any more cards). Then, 1 of your opponent's Digimon gains \"[Start of Your Main Phase] Attack with this Digimon\", until the end of your opponent's turn.",
        "digivolveEffect": "-",
        "securityEffect": "[Security] ＜De-Digivolve  3＞ on 1 of your opponent's Digimon (Trash up to 3 cards from the top of one of your opponent's Digimon. If it has no digivolution cards, or becomes a level 3 Digimon, you can't trash any more cards).",
        "aceEffect": "-",
        "notes": "▹START DECK WAR DRAGON OF COURAGE [ST-15]",
        "color": "Black",
        "version": "Normal",
        "illustrator": "",
        "block": [
            "03"
        ],
        "restriction": "-"
    }
]
